dlt_source_airtable/__init__.py
dlt_source_airtable/api_client.py
dlt_source_airtable/tests/__init__.py
dlt_source_airtable/tests/test_noop.py
dlt_source_airtable-0.0.1.dist-info/METADATA
dlt_source_airtable-0.0.1.dist-info/WHEEL
dlt_source_airtable-0.0.1.dist-info/licenses/LICENSE
dlt_source_airtable-0.0.1.dist-info/RECORD
